{
  "name": "Solarized Light",
  "dark": false,
  "author": "4lex4",
  "editorScheme": "/editor/SolarizedLight.xml",
  "colors": {
    "colorBackground": "#EEE8D5",
    "colorForeground": "#2E4E58",
    "colorInactiveForeground": "#657b83",
    "colorSelectionBackground": "#3570CD",
    "colorSelectionBackgroundInactive": "#cfd0c3",
    "colorSelectionForeground": "#FFFFFF",
    "colorSelectionForegroundInactive": "#2E4E58",
    "colorHoverBackground": "#DBD6C4",
    "colorBorder": "#C0BBAD",
    "colorDisabledForeground": "#839496",
    "colorAlternativeBackground": "#FDF6E3",
    "colorSeparator": "#C9C3B3",
    "colorAcceleratorForeground": "#617EB3",
    "colorAcceleratorSelectionForeground": "#32312D",
    "colorHighlight": "#FFFFFF",
    "colorShadow": "#B5C7CF"
  },
  "ui": {
    "*": {
      "background": "colorBackground",
      "caretForeground": "colorForeground",
      "foreground": "colorForeground",
      "inactiveBackground": "colorBackground",
      "inactiveForeground": "colorInactiveForeground",
      "selectionBackground": "colorSelectionBackground",
      "selectionBackgroundInactive": "colorSelectionBackgroundInactive",
      "selectionForeground": "colorSelectionForeground",
      "selectionForegroundInactive": "colorSelectionForegroundInactive",
      "selectionInactiveBackground": "colorSelectionBackgroundInactive",
      "selectionInactiveForeground": "colorSelectionForegroundInactive",
      "textBackground": "colorBackground",
      "textForeground": "colorForeground"
    },
    "ActionButton": {
      "hoverBackground": "colorHoverBackground",
      "hoverBorderColor": "colorHoverBackground",
      "pressedBackground": "#CCC6B6",
      "pressedBorderColor": "#CCC6B6"
    },
    "Borders": {
      "color": "colorBorder",
      "ContrastBorderColor": "#C6C1B1"
    },
    "Button": {
      "default": {
        "endBackground": "#4681BB",
        "endBorderColor": "#3065A7",
        "focusedBorderColor": "#A5C7E2",
        "foreground": "#FDF6E3",
        "shadowColor": "#000A070F",
        "startBackground": "#4681BB",
        "startBorderColor": "#4676B2"
      },
      "disabledBorderColor": "#CCC6B6",
      "disabledText": "colorDisabledForeground",
      "endBackground": "colorAlternativeBackground",
      "endBorderColor": "#B2AD9F",
      "focusedBorderColor": "#86ABCB",
      "shadowColor": "#000A070F",
      "startBackground": "colorAlternativeBackground",
      "startBorderColor": "#BCB7A8"
    },
    "CheckBoxMenuItem": {
      "acceleratorForeground": "colorAcceleratorForeground",
      "acceleratorSelectionForeground": "colorAcceleratorSelectionForeground",
      "disabledForeground": "colorDisabledForeground"
    },
    "ColorChooser": {
      "swatchesDefaultRecentColor": "#EAE4D1"
    },
    "ComboBox": {
      "ArrowButton": {
        "background": "#F7F0DD",
        "disabledIconColor": "#AAA8A5",
        "iconColor": "#51676e",
        "nonEditableBackground": "colorAlternativeBackground"
      },
      "background" : "colorAlternativeBackground",
      "disabledBackground": "colorBackground",
      "disabledForeground": "#AEAA9C",
      "modifiedItemForeground": "#3961FA",
      "nonEditableBackground": "colorAlternativeBackground"
    },
    "ComboBoxButton": {
      "background": "#FAF3E0"
    },
    "ComboPopup": {
      "border": "1,1,1,1,C0BBAD"
    },
    "CompletionPopup": {
      "foreground": "#colorForeground",
      "matchForeground": "#4975B9",
      "selectionBackground": "#BED8F0",
      "selectionInactiveBackground": "#DCD7C5"
    },
    "Component": {
      "borderColor": "#C3BEAF",
      "disabledBorderColor": "#CCC6B6",
      "errorFocusColor": "#DE3641",
      "focusColor": "#95BDE1",
      "focusedBorderColor": "#86ABCB",
      "hoverIconColor": "#51676e",
      "iconColor": "#51676e",
      "inactiveErrorFocusColor": "#E8B4A6",
      "inactiveWarningFocusColor": "#F6CA7C",
      "infoForeground": "#839496",
      "warningFocusColor": "#DC9E2F"
    },
    "Counter": {
      "background": "#99A6A5B0",
      "foreground": "#002B36"
    },
    "Debugger": {
      "Variables": {
        "changedValueForeground": "#3961FA",
        "collectingDataForeground": "#586e75",
        "errorMessageForeground": "#F94A26",
        "evaluatingExpressionForeground": "#586e75",
        "exceptionForeground": "#F94A26",
        "modifyingValueForeground": "#3961FA",
        "valueForeground": "#C44C30"
      }
    },
    "DebuggerPopup": {
      "borderColor": "colorBorder"
    },
    "DebuggerTabs": {},
    "DefaultTabs": {
      "borderColor": "#C6C1B1",
      "hoverBackground": "#0B08011A",
      "inactiveUnderlineColor": "#99A1A5",
      "underlineColor": "#3D7EC0",
      "underlinedTabBackground": "colorBackground",
      "underlinedTabForeground": "colorForeground"
    },
    "DragAndDrop": {
      "areaBackground": "#DEE3DE",
      "areaBorderColor": "#88ACCD",
      "areaForeground": "#60767d"
    },
    "Editor": {
      "background": "#B5B0A2",
      "foreground": "#4F4D46",
      "shortcutForeground": "#516091"
    },
    "EditorPane": {
      "background": "colorAlternativeBackground",
      "inactiveBackground": "colorAlternativeBackground"
    },
    "EditorTabs": {
      "inactiveColoredFileBackground": "#0B080112",
      "underlinedTabBackground": "#FAF3E0"
    },
    "FileColor": {
      "Blue": "#E8EEE5",
      "Green": "#EDF2CE",
      "Orange": "#F2E0C2",
      "Rose": "#F0D4C2",
      "Violet": "#E4D8D8",
      "Yellow": "#FBF4C9"
    },
    "FlameGraph": {
      "JavaCell": {
        "background": "#F8D583",
        "foreground": "#002B36",
        "hoverBackground": "#E5C67B",
        "searchFailBackground": "#C0A86D",
        "searchFailHoverBackground": "#9A865B",
        "searchOkBackground": "#F8D583",
        "searchOkHoverBackground": "#E5C67B"
      },
      "NativeCell": {
        "background": "#A7D1DD",
        "foreground": "#002B36",
        "hoverBackground": "#98BBCD",
        "searchFailBackground": "#8DADBA",
        "searchFailHoverBackground": "#72858C",
        "searchOkBackground": "#A7D1DD",
        "searchOkHoverBackground": "#98BBCD"
      },
      "ParentCell": {
        "background": "#D7D1C1",
        "foreground": "#002B36",
        "hoverBackground": "#C5C0B1",
        "searchFailBackground": "#8C897E",
        "searchFailHoverBackground": "#AAA598",
        "searchOkBackground": "#D7D1C1",
        "searchOkHoverBackground": "#C5C0B1"
      }
    },
    "FormattedTextField": {
      "background": "colorAlternativeBackground",
      "inactiveBackground": "colorAlternativeBackground"
    },
    "Group": {
      "disabledSeparatorColor": "colorSeparator",
      "separatorColor": "colorSeparator"
    },
    "GutterTooltip": {
      "infoForeground": "#60767d",
      "lineSeparatorColor": "colorBorder"
    },
    "InformationHint": {
      "borderColor": "colorBorder"
    },
    "InplaceRefactoringPopup": {
      "borderColor": "colorBorder"
    },
    "Label": {
      "disabledForeground": "#657b83",
      "disabledText": "#657b83",
      "errorForeground": "#F95551",
      "infoForeground": "#657b83",
      "selectedForeground": "colorForeground"
    },
    "Link": {
      "activeForeground": "#4975B9",
      "hoverForeground": "#4975B9",
      "pressedForeground": "#2857A1",
      "secondaryForeground": "#7598AF",
      "visitedForeground": "#516091"
    },
    "List": {
      "background": "colorAlternativeBackground",
      "dropLineColor": "colorAcceleratorForeground"
    },
    "MemoryIndicator": {
      "allocatedBackground": "#D3CEBD",
      "usedBackground": "#B8B3A5"
    },
    "Menu": {
      "acceleratorForeground": "colorAcceleratorForeground",
      "acceleratorSelectionForeground": "colorAcceleratorSelectionForeground",
      "borderColor": "colorSeparator",
      "disabledBackground": "colorBackground",
      "disabledForeground": "colorDisabledForeground",
      "separatorColor": "colorSeparator"
    },
    "MenuBar": {
      "borderColor": "colorSeparator",
      "disabledBackground": "colorBackground",
      "disabledForeground": "colorDisabledForeground",
      "highlight": "colorHighlight",
      "shadow": "colorShadow"
    },
    "MenuItem": {
      "acceleratorForeground": "colorForeground",
      "disabledBackground": "colorBackground",
      "disabledForeground": "colorDisabledForeground"
    },
    "NavBar": {
      "borderColor": "colorSeparator"
    },
    "Notification": {
      "borderColor": "#B2AD9FCD",
      "errorBackground": "#F2DED1",
      "errorBorderColor": "#DDA195",
      "errorForeground": "colorForeground",
      "MoreButton": {
        "background": "#DFDAC8",
        "foreground": "#586E75",
        "innerBorderColor": "#D7D2C1"
      },
      "ToolWindow": {
        "errorBackground": "#F8C4C5",
        "errorBorderColor": "#D49084",
        "errorForeground": "colorForeground",
        "informativeBackground": "#B4E4A2",
        "informativeBorderColor": "#9DB88A",
        "informativeForeground": "colorForeground",
        "warningBackground": "#F7F280",
        "warningBorderColor": "#B4B21A",
        "warningForeground": "colorForeground"
      }
    },
    "OptionPane": {
      "messageForeground": "colorForeground"
    },
    "Panel": {},
    "ParameterInfo": {
      "background": "#F5F1E5",
      "borderColor": "#DCD7C5",
      "currentOverloadBackground": "#DCD7C5",
      "currentParameterForeground": "#1E1D1B",
      "disabledForeground": "#A7A396",
      "foreground": "#1E1D1B",
      "infoForeground": "#60767d",
      "lineSeparatorColor": "#DCD7C5"
    },
    "PasswordField": {
      "background": "colorAlternativeBackground"
    },
    "Plugins": {
      "background": "colorAlternativeBackground",
      "Button": {
        "installBackground": "colorAlternativeBackground",
        "installBorderColor": "#81BA5C",
        "installFillBackground": "#81BA5C",
        "installFillForeground": "colorAlternativeBackground",
        "installFocusedBackground": "#DFEEC2",
        "installForeground": "#81BA5C",
        "updateBackground": "#5F9DE7",
        "updateBorderColor": "#5F9DE7",
        "updateForeground": "#FDF6E3"
      },
      "disabledForeground": "#B0AB9E",
      "eapTagBackground": "#EECAB6",
      "lightSelectionBackground": "#F3F1E3",
      "SearchField": {
        "background": "colorAlternativeBackground",
        "borderColor": "#C6C0B2"
      },
      "SectionHeader": {
        "background": "#F5EEDC",
        "foreground": "#627880"
      },
      "Tab": {},
      "tagBackground": "#E8E2D2",
      "tagForeground": "#627880"
    },
    "Popup": {
      "Advertiser": {
        "borderColor": "#858177"
      },
      "borderColor": "#6B8086",
      "Header": {
        "activeBackground": "#E2DCCA",
        "inactiveBackground": "#EBE5D2"
      },
      "inactiveBorderColor": "#AAA599",
      "separatorColor": "#B5B0A2",
      "separatorForeground": "#6b8086",
      "Toolbar": {
        "borderColor": "#F5F1E5"
      }
    },
    "PopupMenu": {
      "translucentBackground": "colorBackground"
    },
    "ProgressBar": {
      "failedColor": "#D14943",
      "failedEndColor": "#F6887C",
      "indeterminateEndColor": "#6B8086",
      "indeterminateStartColor": "#C3BEAF",
      "passedColor": "#2DAA66",
      "passedEndColor": "#77DF92",
      "progressColor": "#6B8086",
      "trackColor": "#C3BEAF"
    },
    "RadioButtonMenuItem": {
      "acceleratorForeground": "colorAcceleratorForeground",
      "acceleratorSelectionForeground": "colorAcceleratorSelectionForeground",
      "disabledForeground": "colorDisabledForeground"
    },
    "ScrollBar": {
      "background": "#F5F0E3",
      "hoverThumbBorderColor": "#4b5a5f47",
      "hoverThumbColor": "#5d737b47",
      "hoverTrackColor": "",
      "Mac": {
        "hoverThumbBorderColor": "#002b3680",
        "hoverThumbColor": "#002b3680",
        "hoverTrackColor": "",
        "thumbBorderColor": "#002b3633",
        "thumbColor": "#002b3633",
        "trackColor": "",
        "Transparent": {
          "hoverThumbBorderColor": "#002b3680",
          "hoverThumbColor": "#002b3680",
          "hoverTrackColor": "#6d82891a",
          "thumbBorderColor": "",
          "thumbColor": "",
          "trackColor": ""
        }
      },
      "thumbBorderColor": "#4b5a5f33",
      "thumbColor": "#5d737b33",
      "trackColor": "",
      "Transparent": {
        "hoverThumbBorderColor": "#4b5a5f47",
        "hoverThumbColor": "#5d737b47",
        "hoverTrackColor": "#6d82891a",
        "thumbBorderColor": "#4b5a5f33",
        "thumbColor": "#5d737b33",
        "trackColor": ""
      }
    },
    "ScrollPane": {},
    "SearchEverywhere": {
      "Advertiser": {
        "foreground": "#6B8086"
      },
      "Header": {},
      "List": {
        "separatorColor": "#D8D3C2",
        "separatorForeground": "#657b83"
      },
      "SearchField": {
        "background": "colorAlternativeBackground",
        "borderColor": "#BDB8AA",
        "infoForeground": "#6B8086"
      },
      "Tab": {
        "selectedBackground": "#DAD5C3",
        "selectedForeground": "colorForeground"
      }
    },
    "SearchField": {
      "errorBackground": "#FCC4B3"
    },
    "SearchMatch": {
      "endBackground": "#F8C734",
      "startBackground": "#FAE08D"
    },
    "Separator": {
      "separatorColor": "colorSeparator"
    },
    "SidePanel": {
      "background": "#E2E2D4"
    },
    "Slider": {
      "buttonBorderColor": "#A5A094",
      "buttonColor": "colorAlternativeBackground",
      "tickColor": "#869798",
      "trackColor": "#bec2b9"
    },
    "SpeedSearch": {
      "borderColor": "#6B8086",
      "errorForeground": "#F94A26"
    },
    "Spinner": {},
    "SplitPane": {
      "darkShadow": "#78858B",
      "highlight": "colorBackground",
      "shadow": "colorShadow"
    },
    "SplitPaneDivider": {
      "draggingColor": "#3F3D38"
    },
    "StatusBar": {
      "borderColor": "#8F8B80",
      "hoverBackground": "colorHoverBackground"
    },
    "TabbedPane": {
      "contentAreaColor": "#BCB7A8",
      "disabledForeground": "colorDisabledForeground",
      "disabledUnderlineColor": "#AAA599",
      "focus": "colorAcceleratorForeground",
      "focusColor": "#D6DBD3",
      "hoverColor": "#D5D0BF",
      "underlineColor": "#3D7EC0"
    },
    "Table": {
      "background": "colorAlternativeBackground",
      "dropLineColor": "colorAcceleratorForeground",
      "dropLineShortColor": "colorAcceleratorSelectionForeground",
      "focusCellBackground": "colorAlternativeBackground",
      "focusCellForeground": "colorAcceleratorSelectionForeground",
      "gridColor": "#F5EEDC",
      "lightSelectionBackground": "#E7E6DA",
      "lightSelectionForeground": "colorForeground",
      "lightSelectionInactiveBackground": "#F4EDDA",
      "lightSelectionInactiveForeground": "colorForeground",
      "sortIconColor": "colorShadow",
      "stripeColor": "#F0EBDB"
    },
    "TableHeader": {
      "background": "colorAlternativeBackground",
      "bottomSeparatorColor": "#E1DCCA",
      "separatorColor": "#E1DCCA"
    },
    "TextArea": {
      "background": "colorAlternativeBackground"
    },
    "TextComponent": {},
    "TextField": {
      "background": "colorAlternativeBackground",
      "darkShadow": "#78858B",
      "highlight": "colorHighlight"
    },
    "TextPane": {},
    "TitledBorder": {
      "titleColor": "colorForeground"
    },
    "TitlePane": {
      "Button": {
        "hoverBackground": "#0000001A"
      },
      "inactiveInfoForeground": "#839496",
      "infoForeground": "#586e75"
    },
    "ToggleButton": {
      "borderColor": "#C0BBAD",
      "buttonColor": "#C5C0B0",
      "disabledText": "colorDisabledForeground",
      "offBackground": "colorBackground",
      "offForeground": "#657b83",
      "onBackground": "#6FB460",
      "onForeground": "colorForeground"
    },
    "ToolBar": {
      "darkShadow": "#78858B",
      "floatingForeground": "colorShadow",
      "highlight": "colorHighlight",
      "light": "colorHighlight",
      "shadow": "colorShadow"
    },
    "Toolbar": {
      "Floating": {
        "background": "#EBE5D2"
      }
    },
    "ToolTip": {
      "Actions": {
        "background": "#E9E2CF",
        "infoForeground": "#93a1a1"
      },
      "background": "#F7F0DD",
      "borderColor": "#ADA89A",
      "infoForeground": "#657b83",
      "shortcutForeground": "#566c73"
    },
    "Tooltip": {
      "separatorColor": "#c8cac0"
    },
    "ToolWindow": {
      "Button": {
        "hoverBackground": "#57524228",
        "selectedBackground": "#57524255",
        "selectedForeground": "#002B36"
      },
      "Header": {
        "background": "#DEDDD1",
        "borderColor": "#C6C1B1"
      },
      "HeaderCloseButton": {
        "background": "#B8B3A5"
      },
      "HeaderTab": {
        "selectedInactiveBackground": "#D5D0BF"
      }
    },
    "Tree": {
      "background": "colorAlternativeBackground",
      "errorForeground": "#F94A26",
      "hash": "#E2DCCC",
      "modifiedItemForeground": "#3961FA"
    },
    "ValidationTooltip": {
      "errorBackground": "#F2DED1",
      "errorBorderColor": "#DDA195",
      "warningBackground": "#F2E8D0",
      "warningBorderColor": "#DDC794"
    },
    "VersionControl": {
      "FileHistory": {
        "Commit": {
          "selectedBranchBackground": "#FBF4C7"
        }
      },
      "GitLog": {
        "headIconColor": "#EABE00",
        "localBranchIconColor": "#2DA54A",
        "otherIconColor": "#627880",
        "remoteBranchIconColor": "#976EA1",
        "tagIconColor": "#627880"
      },
      "HgLog": {
        "bookmarkIconColor": "#976EA1",
        "branchIconColor": "#2DA54A",
        "closedBranchIconColor": "#7B2A2D",
        "headIconColor": "#832460",
        "localTagIconColor": "#008687",
        "mqTagIconColor": "#002C8B",
        "tagIconColor": "#627880",
        "tipIconColor": "#EABE00"
      },
      "Log": {
        "Commit": {
          "currentBranchBackground": "#E3F2E4",
          "unmatchedForeground": "#6b8086"
        }
      },
      "RefLabel": {
        "backgroundBase": "#000000",
        "foreground": "#627880"
      }
    },
    "Viewport": {},
    "WelcomeScreen": {
      "background": "#F7F0DD",
      "borderColor": "#BEB9AA",
      "captionBackground": "#D2CCBC",
      "captionForeground": "colorForeground",
      "footerBackground": "#D2CCBC",
      "footerForeground": "colorForeground",
      "groupIconBorderColor": "#BEB9AA",
      "headerBackground": "#DDD7C4",
      "headerForeground": "#3c5158",
      "Projects": {
        "background": "colorAlternativeBackground",
        "selectionInactiveBackground": "#DAD4C1"
      },
      "separatorColor": "#ECE5D3"
    },
    "Window": {
      "border": "colorBorder"
    }
  },
  "icons": {
    "ColorPalette": {
      "Actions.Red": "#dc322f",
      "Actions.Yellow": "#b58900",
      "Actions.Green": "#859900",
      "Actions.Blue": "#268bd2",
      "Actions.Grey": "#586e75",
      "Actions.GreyInline": "#586e75",
      "Objects.Grey": "#657b83",
      "Objects.Blue": "#268bd2",
      "Objects.Green": "#859900",
      "Objects.Yellow": "#b58900",
      "Objects.YellowDark": "#cb4b16",
      "Objects.Purple": "#6c71c4",
      "Objects.Pink": "#d33682",
      "Objects.Red": "#dc322f",
      "Objects.RedStatus": "#dc322f",
      "Objects.BlackText": "#002b36ff",
      "Objects.GreenAndroid": "#859900",
      "Checkbox.Background.Default": "#FDF6E3",
      "Checkbox.Border.Default": "#BDB8AA",
      "Checkbox.Background.Selected": "#4984BE",
      "Checkbox.Border.Selected": "#4984BE",
      "Checkbox.Foreground.Selected": "#FDF6E3",
      "Checkbox.Background.Disabled": "#EEE8D5",
      "Checkbox.Border.Disabled": "#CCC6B6",
      "Checkbox.Foreground.Disabled": "#839496",
      "Checkbox.Focus.Thin.Default": "#86ABCB",
      "Checkbox.Focus.Thin.Selected": "#86ABCB",
      "Checkbox.Focus.Wide": "#86ABCB"
    }
  }
}